{
  "_class": "symbolInstance",
  "booleanOperation": 0,
  "clippingMaskMode": 0,
  "do_objectID": "9174197C-B4CB-46D5-90FB-1D1A7CC0760C",
  "exportOptions": {
    "_class": "exportOptions",
    "do_objectID": "2FC887F5-0E0A-4016-9B78-FA264149E1EE",
    "exportFormats": [
    ],
    "includedLayerIds": [
    ],
    "layerOptions": 0,
    "shouldTrim": false
  },
  "frame": {
    "_class": "rect",
    "constrainProportions": false,
    "do_objectID": "86653487-8FFD-4D55-9D98-E5412D98EFBA",
    "height": 40,
    "width": 278,
    "x": 0,
    "y": 0
  },
  "hasClippingMask": false,
  "horizontalSpacing": 0,
  "isFixedToViewport": false,
  "isFlippedHorizontal": false,
  "isFlippedVertical": false,
  "isLocked": false,
  "isVisible": true,
  "layerListExpandedType": 0,
  "name": "Color/Functional/White Copy",
  "nameIsFixed": false,
  "overrideValues": [
  ],
  "resizingConstraint": 63,
  "resizingType": 0,
  "rotation": 0,
  "scale": 1,
  "shouldBreakMaskChain": false,
  "style": {
    "_class": "style",
    "do_objectID": "B99083C2-2E87-45D8-BC33-63E8627D9628",
    "endMarkerType": 0,
    "miterLimit": 10,
    "startMarkerType": 0,
    "windingRule": 1
  },
  "symbolID": "BFF391FF-6571-429D-9E1B-0C1299AAA063",
  "verticalSpacing": 0
}