{
  "_class": "shapePath",
  "booleanOperation": -1,
  "clippingMaskMode": 0,
  "do_objectID": "A57EAB95-E428-45E8-AC5F-4D9C38C21502",
  "edited": true,
  "exportOptions": {
    "_class": "exportOptions",
    "do_objectID": "03F45344-8F05-4716-A0AB-8B29550F6A8E",
    "exportFormats": [
    ],
    "includedLayerIds": [
    ],
    "layerOptions": 0,
    "shouldTrim": false
  },
  "frame": {
    "_class": "rect",
    "constrainProportions": true,
    "do_objectID": "4D9DB823-13EC-4D40-9CD7-FDB5D279C7E8",
    "height": 16.000001,
    "width": 19.99999875000016,
    "x": 0,
    "y": 0
  },
  "hasClippingMask": true,
  "isClosed": true,
  "isFixedToViewport": false,
  "isFlippedHorizontal": false,
  "isFlippedVertical": false,
  "isLocked": false,
  "isVisible": true,
  "layerListExpandedType": 0,
  "name": "Mask",
  "nameIsFixed": false,
  "pointRadiusBehaviour": 1,
  "points": [
    {
      "_class": "curvePoint",
      "cornerRadius": 0,
      "curveFrom": "{0.60000000000000009, 0.93374992078126029}",
      "curveMode": 1,
      "curveTo": "{0.60000000000000009, 0.93374992078126029}",
      "hasCurveFrom": false,
      "hasCurveTo": false,
      "point": "{0.60000000000000009, 0.93374992078126029}"
    },
    {
      "_class": "curvePoint",
      "cornerRadius": 0,
      "curveFrom": "{0.32200003000000016, 0.66000000499999956}",
      "curveMode": 4,
      "curveTo": "{0.60000000000000009, 0.66000000499999956}",
      "hasCurveFrom": true,
      "hasCurveTo": false,
      "point": "{0.60000000000000009, 0.66000000499999956}"
    },
    {
      "_class": "curvePoint",
      "cornerRadius": 0,
      "curveFrom": "{0.055999989999999944, 0.66625002921874643}",
      "curveMode": 4,
      "curveTo": "{0.13899993999999996, 0.76625004171874489}",
      "hasCurveFrom": true,
      "hasCurveTo": true,
      "point": "{0, 1}"
    },
    {
      "_class": "curvePoint",
      "cornerRadius": 0,
      "curveFrom": "{0.60000000000000009, 0.26625010421873702}",
      "curveMode": 4,
      "curveTo": "{0.21099997000000004, 0.3337500832812394}",
      "hasCurveFrom": false,
      "hasCurveTo": true,
      "point": "{0.60000000000000009, 0.26625010421873702}"
    },
    {
      "_class": "curvePoint",
      "cornerRadius": 0,
      "curveFrom": "{0.60000000000000009, 0}",
      "curveMode": 1,
      "curveTo": "{0.60000000000000009, 0}",
      "hasCurveFrom": false,
      "hasCurveTo": false,
      "point": "{0.60000000000000009, 0}"
    },
    {
      "_class": "curvePoint",
      "cornerRadius": 0,
      "curveFrom": "{1, 0.4662498792187651}",
      "curveMode": 1,
      "curveTo": "{1, 0.4662498792187651}",
      "hasCurveFrom": false,
      "hasCurveTo": false,
      "point": "{1, 0.4662498792187651}"
    },
    {
      "_class": "curvePoint",
      "cornerRadius": 0,
      "curveFrom": "{0.60000000000000009, 0.93374979578127559}",
      "curveMode": 1,
      "curveTo": "{0.60000000000000009, 0.93374979578127559}",
      "hasCurveFrom": false,
      "hasCurveTo": false,
      "point": "{0.60000000000000009, 0.93374979578127559}"
    }
  ],
  "resizingConstraint": 63,
  "resizingType": 0,
  "rotation": 0,
  "shouldBreakMaskChain": false,
  "style": {
    "_class": "style",
    "do_objectID": "195C471C-B468-4635-84D5-BFA6282F9D3B",
    "endMarkerType": 0,
    "miterLimit": 10,
    "startMarkerType": 0,
    "windingRule": 1
  }
}