{
  "_class": "text",
  "attributedString": {
    "_class": "attributedString",
    "attributes": [
      {
        "_class": "stringAttribute",
        "attributes": {
          "MSAttributedStringColorAttribute": {
            "_class": "color",
            "alpha": 1,
            "blue": 0.1990772192028986,
            "green": 0.1990772192028986,
            "red": 0.1990772192028986
          },
          "MSAttributedStringFontAttribute": {
            "_class": "fontDescriptor",
            "attributes": {
              "name": "Roboto-Regular",
              "size": 18
            }
          },
          "MSAttributedStringStrokeColorAttribute": {
            "_class": "color",
            "alpha": 1,
            "blue": 0.2,
            "green": 0.2,
            "red": 0.2
          },
          "kerning": 0,
          "paragraphStyle": {
            "_class": "paragraphStyle",
            "allowsDefaultTighteningForTruncation": 0,
            "baseWritingDirection": 0,
            "maximumLineHeight": 22,
            "minimumLineHeight": 22
          },
          "strokeWidth": 0
        },
        "length": 68,
        "location": 0
      }
    ],
    "string": "In hac habitasse platea dictumst. Vivamus adipiscing fermentum quam."
  },
  "automaticallyDrawOnUnderlyingPath": false,
  "booleanOperation": 0,
  "clippingMaskMode": 0,
  "do_objectID": "916C6FF4-A729-4E75-A258-9D439C6BEA98",
  "dontSynchroniseWithSymbol": false,
  "exportOptions": {
    "_class": "exportOptions",
    "exportFormats": [
    ],
    "includedLayerIds": [
    ],
    "layerOptions": 0,
    "shouldTrim": false
  },
  "frame": {
    "_class": "rect",
    "constrainProportions": false,
    "height": 44,
    "width": 320,
    "x": 960,
    "y": 115
  },
  "glyphBounds": "{{0, 3}, {303, 40}}",
  "hasClippingMask": false,
  "isFixedToViewport": false,
  "isFlippedHorizontal": false,
  "isFlippedVertical": false,
  "isLocked": false,
  "isVisible": true,
  "layerListExpandedType": 0,
  "lineSpacingBehaviour": 2,
  "maintainScrollPosition": false,
  "name": "In hac habitasse pla",
  "nameIsFixed": false,
  "originalObjectID": "9908C7BB-DC4B-47D2-BE66-8CC366F39FDF",
  "resizingConstraint": 63,
  "resizingType": 0,
  "rotation": 0,
  "sharedStyleID": "5E700ABD-F913-42A2-9361-6A4C1A1849FC",
  "shouldBreakMaskChain": false,
  "style": {
    "_class": "style",
    "blur": {
      "_class": "blur",
      "center": "{0.5, 0.5}",
      "isEnabled": false,
      "motionAngle": 0,
      "radius": 10,
      "saturation": 1,
      "type": 0
    },
    "borderOptions": {
      "_class": "borderOptions",
      "dashPattern": [
      ],
      "isEnabled": true,
      "lineCapStyle": 0,
      "lineJoinStyle": 0
    },
    "borders": [
    ],
    "colorControls": {
      "_class": "colorControls",
      "brightness": 0,
      "contrast": 1,
      "hue": 0,
      "isEnabled": true,
      "saturation": 1
    },
    "contextSettings": {
      "_class": "graphicsContextSettings",
      "blendMode": 0,
      "opacity": 1
    },
    "do_objectID": "B1FB8F8B-6152-4EA3-91CF-0018A7434E79",
    "endMarkerType": 0,
    "fills": [
    ],
    "innerShadows": [
    ],
    "miterLimit": 10,
    "shadows": [
    ],
    "startMarkerType": 0,
    "textStyle": {
      "_class": "textStyle",
      "encodedAttributes": {
        "MSAttributedStringColorAttribute": {
          "_class": "color",
          "alpha": 1,
          "blue": 0.1990772192028986,
          "green": 0.1990772192028986,
          "red": 0.1990772192028986
        },
        "MSAttributedStringFontAttribute": {
          "_class": "fontDescriptor",
          "attributes": {
            "name": "Roboto-Regular",
            "size": 18
          }
        },
        "MSAttributedStringStrokeColorAttribute": {
          "_class": "color",
          "alpha": 1,
          "blue": 0.2,
          "green": 0.2,
          "red": 0.2
        },
        "kerning": 0,
        "paragraphStyle": {
          "_class": "paragraphStyle",
          "allowsDefaultTighteningForTruncation": 0,
          "baseWritingDirection": 0,
          "maximumLineHeight": 22,
          "minimumLineHeight": 22
        },
        "strokeWidth": 0
      },
      "verticalAlignment": 0
    },
    "windingRule": 1
  },
  "textBehaviour": 1
}