{
  "_class": "shapePath",
  "booleanOperation": -1,
  "clippingMaskMode": 0,
  "do_objectID": "64ECCD25-D283-49E8-825B-0CDB06F13B7D",
  "edited": true,
  "exportOptions": {
    "_class": "exportOptions",
    "do_objectID": "941AED05-3FB7-4525-AFFC-4A9DCD6699E7",
    "exportFormats": [
    ],
    "includedLayerIds": [
    ],
    "layerOptions": 0,
    "shouldTrim": false
  },
  "frame": {
    "_class": "rect",
    "constrainProportions": false,
    "do_objectID": "95F89764-8769-442F-B320-7BE0612909C3",
    "height": 15.99999904,
    "width": 15.99999904,
    "x": 0,
    "y": 3.999999759999998
  },
  "hasClippingMask": false,
  "isClosed": true,
  "isFixedToViewport": false,
  "isFlippedHorizontal": false,
  "isFlippedVertical": false,
  "isLocked": false,
  "isVisible": true,
  "layerListExpandedType": 0,
  "name": "Path",
  "nameIsFixed": false,
  "pointRadiusBehaviour": 1,
  "points": [
    {
      "_class": "curvePoint",
      "cornerRadius": 0,
      "curveFrom": "{0, 0}",
      "curveMode": 1,
      "curveTo": "{0, 0}",
      "hasCurveFrom": false,
      "hasCurveTo": false,
      "point": "{0, 0}"
    },
    {
      "_class": "curvePoint",
      "cornerRadius": 0,
      "curveFrom": "{0, 0.9437500000000002}",
      "curveMode": 4,
      "curveTo": "{0, 0.875}",
      "hasCurveFrom": true,
      "hasCurveTo": false,
      "point": "{0, 0.875}"
    },
    {
      "_class": "curvePoint",
      "cornerRadius": 0,
      "curveFrom": "{0.12500000000000003, 1}",
      "curveMode": 4,
      "curveTo": "{0.056250006249999984, 1}",
      "hasCurveFrom": false,
      "hasCurveTo": true,
      "point": "{0.12500000000000003, 1}"
    },
    {
      "_class": "curvePoint",
      "cornerRadius": 0,
      "curveFrom": "{1, 1}",
      "curveMode": 1,
      "curveTo": "{1, 1}",
      "hasCurveFrom": false,
      "hasCurveTo": false,
      "point": "{1, 1}"
    },
    {
      "_class": "curvePoint",
      "cornerRadius": 0,
      "curveFrom": "{1, 0.875}",
      "curveMode": 1,
      "curveTo": "{1, 0.875}",
      "hasCurveFrom": false,
      "hasCurveTo": false,
      "point": "{1, 0.875}"
    },
    {
      "_class": "curvePoint",
      "cornerRadius": 0,
      "curveFrom": "{0.12500000000000003, 0.875}",
      "curveMode": 1,
      "curveTo": "{0.12500000000000003, 0.875}",
      "hasCurveFrom": false,
      "hasCurveTo": false,
      "point": "{0.12500000000000003, 0.875}"
    },
    {
      "_class": "curvePoint",
      "cornerRadius": 0,
      "curveFrom": "{0.12500000000000003, 0}",
      "curveMode": 1,
      "curveTo": "{0.12500000000000003, 0}",
      "hasCurveFrom": false,
      "hasCurveTo": false,
      "point": "{0.12500000000000003, 0}"
    }
  ],
  "resizingConstraint": 63,
  "resizingType": 0,
  "rotation": 0,
  "shouldBreakMaskChain": false,
  "style": {
    "_class": "style",
    "do_objectID": "F077DE7A-5A2F-48AF-8F99-F92ECF4CAD22",
    "endMarkerType": 0,
    "miterLimit": 10,
    "startMarkerType": 0,
    "windingRule": 1
  }
}