{
  "_class": "symbolMaster",
  "allowsOverrides": true,
  "backgroundColor": {
    "_class": "color",
    "alpha": 1,
    "blue": 1,
    "do_objectID": "2683D19B-764B-4A00-A3AB-964FAC9ECCA8",
    "green": 1,
    "red": 1
  },
  "booleanOperation": 0,
  "changeIdentifier": 1705,
  "clippingMaskMode": 0,
  "do_objectID": "BB806D53-E739-4A81-BB08-AF6D3E4584CE",
  "exportOptions": {
    "_class": "exportOptions",
    "do_objectID": "932CD13B-6F57-4191-8D5D-322D8791D6CB",
    "exportFormats": [
    ],
    "includedLayerIds": [
    ],
    "layerOptions": 0,
    "shouldTrim": false
  },
  "frame": {
    "_class": "rect",
    "constrainProportions": false,
    "do_objectID": "830335E7-4EDC-4992-B2CC-C5570CE33C00",
    "height": 24,
    "width": 24,
    "x": 880,
    "y": 701
  },
  "groupLayout": {
    "_class": "MSImmutableFreeformGroupLayout"
  },
  "hasBackgroundColor": false,
  "hasClickThrough": true,
  "hasClippingMask": false,
  "horizontalRulerData": {
    "_class": "rulerData",
    "base": 0,
    "do_objectID": "2AC793A6-80A0-47DF-8A51-E3DDC69C4D2D",
    "guides": [
    ]
  },
  "includeBackgroundColorInExport": true,
  "includeBackgroundColorInInstance": false,
  "includeInCloudUpload": true,
  "isFixedToViewport": false,
  "isFlippedHorizontal": false,
  "isFlippedVertical": false,
  "isFlowHome": false,
  "isLocked": false,
  "isVisible": true,
  "layerListExpandedType": 2,
  "layers": [
    {
      "class": "group",
      "id": "41F9A510-ED45-4539-9598-E3B2630111A5"
    }
  ],
  "name": "Icon/List",
  "nameIsFixed": true,
  "originalObjectID": "84EE06E4-2C00-4516-9167-93BF9B1DE47F",
  "overrideProperties": [
    {
      "_class": "MSImmutableOverrideProperty",
      "canOverride": true,
      "overrideName": "FC22AF7D-A1F7-4C3F-9869-E47C666F4F04_symbolID"
    }
  ],
  "resizesContent": false,
  "resizingConstraint": 63,
  "resizingType": 0,
  "rotation": 0,
  "shouldBreakMaskChain": true,
  "style": {
    "_class": "style",
    "do_objectID": "A6EDD322-838A-4B7C-B248-43B1A7F0AE2B",
    "endMarkerType": 0,
    "miterLimit": 10,
    "startMarkerType": 0,
    "windingRule": 1
  },
  "symbolID": "83273D18-BAEA-4E37-8827-17285E322692",
  "userInfo": {
    "com.animaapp.stc-sketch-plugin": {
      "kModelPropertiesKey": {
      }
    }
  },
  "verticalRulerData": {
    "_class": "rulerData",
    "base": 0,
    "do_objectID": "ABF13786-6470-4B49-9E20-F1621D6A9DD6",
    "guides": [
    ]
  }
}