{
  "_class": "group",
  "booleanOperation": 0,
  "clippingMaskMode": 0,
  "do_objectID": "FF0152A1-ADFE-465D-BE1D-42540257157C",
  "exportOptions": {
    "_class": "exportOptions",
    "do_objectID": "B35DF80F-852E-4B82-9BD7-453BBDD24FD6",
    "exportFormats": [
    ],
    "includedLayerIds": [
    ],
    "layerOptions": 0,
    "shouldTrim": false
  },
  "frame": {
    "_class": "rect",
    "constrainProportions": false,
    "do_objectID": "43276869-3155-4EAA-AE1E-204915995A56",
    "height": 20,
    "width": 20,
    "x": 2,
    "y": 2
  },
  "groupLayout": {
    "_class": "MSImmutableFreeformGroupLayout"
  },
  "hasClickThrough": false,
  "hasClippingMask": false,
  "isFixedToViewport": false,
  "isFlippedHorizontal": false,
  "isFlippedVertical": false,
  "isLocked": false,
  "isVisible": true,
  "layerListExpandedType": 2,
  "layers": [
    {
      "class": "group",
      "id": "7061E090-B4F5-4B9B-B28B-A9BA98AF8EC3"
    }
  ],
  "name": "Color/Primary/100%",
  "nameIsFixed": false,
  "resizingConstraint": 63,
  "resizingType": 0,
  "rotation": 0,
  "shouldBreakMaskChain": false,
  "style": {
    "_class": "style",
    "do_objectID": "A857C618-8EB6-4EDE-BFF3-18D9B4A4E021",
    "endMarkerType": 0,
    "miterLimit": 10,
    "startMarkerType": 0,
    "windingRule": 1
  }
}